{
  "R477946" : {
    "routeId" : "R477946",
    "airline" : "AirlineBB",
    "durationHours" : 5.0,
    "distanceKm" : 717.0,
    "price" : 820.0,
    "departureTime" : [ 21, 54 ],
    "arrivalTime" : [ 2, 54 ],
    "originAirportCode" : 14,
    "destinationAirportCode" : 28
  },
  "R118013" : {
    "routeId" : "R118013",
    "airline" : "AirlineGJ",
    "durationHours" : 6.0,
    "distanceKm" : 3128.0,
    "price" : 723.0,
    "departureTime" : [ 2, 42 ],
    "arrivalTime" : [ 8, 42 ],
    "originAirportCode" : 25,
    "destinationAirportCode" : 30
  },
  "R637872" : {
    "routeId" : "R637872",
    "airline" : "AirlineLY",
    "durationHours" : 4.0,
    "distanceKm" : 2646.0,
    "price" : 182.0,
    "departureTime" : [ 12, 38 ],
    "arrivalTime" : [ 16, 38 ],
    "originAirportCode" : 23,
    "destinationAirportCode" : 14
  },
  "R663059" : {
    "routeId" : "R663059",
    "airline" : "AirlineDM",
    "durationHours" : 3.0,
    "distanceKm" : 3606.0,
    "price" : 560.0,
    "departureTime" : [ 1, 44 ],
    "arrivalTime" : [ 4, 44 ],
    "originAirportCode" : 30,
    "destinationAirportCode" : 21
  },
  "R811969" : {
    "routeId" : "R811969",
    "airline" : "AirlineXF",
    "durationHours" : 8.0,
    "distanceKm" : 3176.0,
    "price" : 924.0,
    "departureTime" : [ 10, 0 ],
    "arrivalTime" : [ 18, 0 ],
    "originAirportCode" : 25,
    "destinationAirportCode" : 12
  },
  "R992201" : {
    "routeId" : "R992201",
    "airline" : "AirlineFT",
    "durationHours" : 6.0,
    "distanceKm" : 4904.0,
    "price" : 435.0,
    "departureTime" : [ 18, 40 ],
    "arrivalTime" : [ 0, 40 ],
    "originAirportCode" : 27,
    "destinationAirportCode" : 20
  },
  "R305993" : {
    "routeId" : "R305993",
    "airline" : "AirlinePD",
    "durationHours" : 4.0,
    "distanceKm" : 3676.0,
    "price" : 616.0,
    "departureTime" : [ 5, 13 ],
    "arrivalTime" : [ 9, 13 ],
    "originAirportCode" : 19,
    "destinationAirportCode" : 23
  },
  "R139890" : {
    "routeId" : "R139890",
    "airline" : "AirlineWI",
    "durationHours" : 4.0,
    "distanceKm" : 2508.0,
    "price" : 856.0,
    "departureTime" : [ 0, 35 ],
    "arrivalTime" : [ 4, 35 ],
    "originAirportCode" : 28,
    "destinationAirportCode" : 27
  },
  "R699226" : {
    "routeId" : "R699226",
    "airline" : "AirlineKB",
    "durationHours" : 2.0,
    "distanceKm" : 5236.0,
    "price" : 978.0,
    "departureTime" : [ 2, 16 ],
    "arrivalTime" : [ 4, 16 ],
    "originAirportCode" : 14,
    "destinationAirportCode" : 19
  },
  "R539584" : {
    "routeId" : "R539584",
    "airline" : "AirlineFR",
    "durationHours" : 7.0,
    "distanceKm" : 3225.0,
    "price" : 744.0,
    "departureTime" : [ 1, 15 ],
    "arrivalTime" : [ 8, 15 ],
    "originAirportCode" : 19,
    "destinationAirportCode" : 23
  },
  "R539125" : {
    "routeId" : "R539125",
    "airline" : "AirlineFJ",
    "durationHours" : 8.0,
    "distanceKm" : 3717.0,
    "price" : 804.0,
    "departureTime" : [ 21, 2 ],
    "arrivalTime" : [ 5, 2 ],
    "originAirportCode" : 14,
    "destinationAirportCode" : 17
  },
  "R538301" : {
    "routeId" : "R538301",
    "airline" : "AirlineIZ",
    "durationHours" : 10.0,
    "distanceKm" : 3289.0,
    "price" : 359.0,
    "departureTime" : [ 23, 15 ],
    "arrivalTime" : [ 9, 15 ],
    "originAirportCode" : 20,
    "destinationAirportCode" : 11
  },
  "R783991" : {
    "routeId" : "R783991",
    "airline" : "AirlineKX",
    "durationHours" : 3.0,
    "distanceKm" : 1210.0,
    "price" : 689.0,
    "departureTime" : [ 4, 32 ],
    "arrivalTime" : [ 7, 32 ],
    "originAirportCode" : 24,
    "destinationAirportCode" : 21
  },
  "R137875" : {
    "routeId" : "R137875",
    "airline" : "AirlineCM",
    "durationHours" : 9.0,
    "distanceKm" : 2482.0,
    "price" : 654.0,
    "departureTime" : [ 17, 36 ],
    "arrivalTime" : [ 2, 36 ],
    "originAirportCode" : 12,
    "destinationAirportCode" : 28
  },
  "R311602" : {
    "routeId" : "R311602",
    "airline" : "AirlineVV",
    "durationHours" : 9.0,
    "distanceKm" : 5253.0,
    "price" : 792.0,
    "departureTime" : [ 3, 42 ],
    "arrivalTime" : [ 12, 42 ],
    "originAirportCode" : 27,
    "destinationAirportCode" : 11
  },
  "R850701" : {
    "routeId" : "R850701",
    "airline" : "AirlineUO",
    "durationHours" : 1.0,
    "distanceKm" : 3112.0,
    "price" : 261.0,
    "departureTime" : [ 15, 28 ],
    "arrivalTime" : [ 16, 28 ],
    "originAirportCode" : 16,
    "destinationAirportCode" : 19
  },
  "R16844" : {
    "routeId" : "R16844",
    "airline" : "AirlineRB",
    "durationHours" : 2.0,
    "distanceKm" : 4221.0,
    "price" : 425.0,
    "departureTime" : [ 2, 5 ],
    "arrivalTime" : [ 4, 5 ],
    "originAirportCode" : 19,
    "destinationAirportCode" : 22
  },
  "R207748" : {
    "routeId" : "R207748",
    "airline" : "AirlineJO",
    "durationHours" : 2.0,
    "distanceKm" : 4017.0,
    "price" : 797.0,
    "departureTime" : [ 20, 30 ],
    "arrivalTime" : [ 22, 30 ],
    "originAirportCode" : 21,
    "destinationAirportCode" : 28
  },
  "R295398" : {
    "routeId" : "R295398",
    "airline" : "AirlineWI",
    "durationHours" : 10.0,
    "distanceKm" : 4736.0,
    "price" : 706.0,
    "departureTime" : [ 11, 27 ],
    "arrivalTime" : [ 21, 27 ],
    "originAirportCode" : 17,
    "destinationAirportCode" : 28
  },
  "R533471" : {
    "routeId" : "R533471",
    "airline" : "AirlineUM",
    "durationHours" : 6.0,
    "distanceKm" : 3572.0,
    "price" : 325.0,
    "departureTime" : [ 1, 49 ],
    "arrivalTime" : [ 7, 49 ],
    "originAirportCode" : 24,
    "destinationAirportCode" : 28
  }
}